buildingid/__init__.py
buildingid/code.py
buildingid/code_pattern.py
buildingid/command_line/__init__.py
buildingid/command_line/dict_datum.py
buildingid/command_line/dict_decoders.py
buildingid/command_line/dict_encoders.py
buildingid/command_line/dict_pipe.py
buildingid/command_line/exceptions.py
buildingid/command_line/set_csv_field_size_limit.py
buildingid/validators.py
buildingid-2.3.0.dist-info/licenses/LICENSE.txt
buildingid-2.3.0.dist-info/WHEEL
buildingid-2.3.0.dist-info/entry_points.txt
buildingid-2.3.0.dist-info/METADATA
buildingid-2.3.0.dist-info/RECORD
