Metadata-Version: 2.4
Name: buildingid
Version: 2.3.0
Summary: Unique Building Identifier (UBID)
Author: Mark Borkum, Nicholas Long, Katherine Fleming, Alex Swindler
Author-email: Mark Borkum <mark.borkum@pnnl.gov>, Nicholas Long <nicholas.long@nlr.gov>, Katherine Fleming <katherine.fleming@nlr.gov>, Alex Swindler <alex.swindler@nlr.gov>
License-Expression: BSD-2-Clause
License-File: LICENSE.txt
Classifier: Development Status :: 5 - Production/Stable
Classifier: Intended Audience :: Developers
Classifier: Topic :: Scientific/Engineering :: GIS
Classifier: Operating System :: OS Independent
Classifier: Programming Language :: Python :: 3
Classifier: Programming Language :: Python :: 3 :: Only
Classifier: Programming Language :: Python :: 3.11
Classifier: Programming Language :: Python :: 3.12
Classifier: Programming Language :: Python :: 3.13
Classifier: Programming Language :: Python :: 3.14
Requires-Dist: click>=8.3.0
Requires-Dist: click-log>=0.4.0
Requires-Dist: openlocationcode>=1.0.0
Requires-Dist: pandas>=3.0.0
Requires-Dist: pyqtree>=1.0.0
Requires-Dist: shapely>=2.0.0
Requires-Dist: tldm==1.1.0
Requires-Python: >=3.11
